joke_stat_sales/__init__.py
joke_stat_sales/__main__.py
joke_stat_sales/test.py
joke_stat_sales-0.1.0.dist-info/METADATA
joke_stat_sales-0.1.0.dist-info/WHEEL
joke_stat_sales-0.1.0.dist-info/top_level.txt
joke_stat_sales-0.1.0.dist-info/RECORD
