Metadata-Version: 2.1
Name: joke_stat_sales
Version: 0.1.0
Summary: Быстрая оценка продаж в формате csv
Author-email: Pablo_3_16 <p.ergle@edu.centraluniversity.ru>
License: MIT
Requires-Python: >=3.12
Requires-Dist: pandas>=2.2.3
